nekosbest_revive/__init__.py
nekosbest_revive/client.py
nekosbest_revive/errors.py
nekosbest_revive/http.py
nekosbest_revive/models.py
nekosbest_revive/types.py
nekosbest_revive-1.1.13.dist-info/LICENSE
nekosbest_revive-1.1.13.dist-info/METADATA
nekosbest_revive-1.1.13.dist-info/WHEEL
nekosbest_revive-1.1.13.dist-info/top_level.txt
nekosbest_revive-1.1.13.dist-info/RECORD
