Metadata-Version: 2.1
Name: nekosbest_revive
Version: 1.1.13
Summary: A simple async Python wrapper for nekos.best API
Home-page: https://github.com/okineadev/nekos-best
Author: Okinea Dev
License: AGPLv3
Project-URL: Issue Tracker, https://github.com/okineadev/nekos-best/issues
Project-URL: Source Code, https://github.com/okineadev/nekos-best
Classifier: Development Status :: 5 - Production/Stable
Classifier: Framework :: AsyncIO
Classifier: Intended Audience :: Developers
Classifier: License :: OSI Approved :: GNU Affero General Public License v3 or later (AGPLv3+)
Classifier: Natural Language :: English
Classifier: Operating System :: OS Independent
Classifier: Programming Language :: Python :: 3.8
Classifier: Programming Language :: Python :: 3.9
Classifier: Programming Language :: Python :: 3.10
Classifier: Programming Language :: Python :: 3.11
Classifier: Topic :: Internet
Classifier: Topic :: Software Development :: Libraries
Classifier: Topic :: Software Development :: Libraries :: Python Modules
Classifier: Topic :: Utilities
Requires-Python: >=3.8
License-File: LICENSE
Requires-Dist: aiohttp >=3.6.2
